[
  {
    "__type__": "GlucoseStatusAutoIsf",
    "glucose": 131.0,
    "noise": 0.0,
    "delta": 4.33,
    "shortAvgDelta": 4.94,
    "longAvgDelta": 3.84,
    "date": 1768471810642,
    "bgAcceleration": -0.6666666666666643,
    "duraISFminutes": 5.0,
    "duraISFaverage": 128.8,
    "parabolaMinutes": 15.0,
    "deltaPl": 4.733333333333736,
    "deltaPn": 4.066666666667071,
    "a0": 131.1,
    "a1": 4.4,
    "a2": -0.33,
    "corrSqu": 0.9986,
    "_log_path": "C:\\Users\\IngPPO1\\Desktop\\AAPS-Emulator\\data\\logs\\AndroidAPS.2026-01-15.0.log.zip"
  },
  {
    "__type__": "CurrentTemp",
    "duration": 26,
    "rate": 0.75,
    "minutesrunning": 4,
    "_log_path": "C:\\Users\\IngPPO1\\Desktop\\AAPS-Emulator\\data\\logs\\AndroidAPS.2026-01-15.0.log.zip"
  },
  {
    "__type__": "IobTotal",
    "time": 1768471829635,
    "iob": 1.801,
    "activity": 0.0083,
    "bolussnooze": 0.0,
    "basaliob": -0.172,
    "netbasalinsulin": -1.048,
    "hightempinsulin": 0.511,
    "lastBolusTime": 1768471607477,
    "iobWithZeroTemp": {
      "__type__": "IobTotal",
      "time": 1768471829635,
      "iob": 1.801,
      "activity": 0.0083,
      "bolussnooze": 0.0,
      "basaliob": -0.172,
      "netbasalinsulin": -1.048,
      "hightempinsulin": 0.511,
      "lastBolusTime": 1768471607477,
      "iobWithZeroTemp": null,
      "netInsulin": -1.048,
      "extendedBolusInsulin": 0.0
    },
    "netInsulin": -1.048,
    "extendedBolusInsulin": 0.0,
    "_log_path": "C:\\Users\\IngPPO1\\Desktop\\AAPS-Emulator\\data\\logs\\AndroidAPS.2026-01-15.0.log.zip"
  },
  {
    "__type__": "OapsProfileAutoIsf",
    "dia": 0.0,
    "min_5m_carbimpact": 0.0,
    "max_iob": 10.0,
    "max_daily_basal": 0.8,
    "max_basal": 2.4,
    "min_bg": 90.0,
    "max_bg": 90.0,
    "target_bg": 90.0,
    "carb_ratio": 15.8,
    "sens": 86.39999999999999,
    "autosens_adjust_targets": false,
    "max_daily_safety_multiplier": 3.0,
    "current_basal_safety_multiplier": 4.0,
    "high_temptarget_raises_sensitivity": true,
    "low_temptarget_lowers_sensitivity": true,
    "sensitivity_raises_target": true,
    "resistance_lowers_target": true,
    "adv_target_adjustments": false,
    "exercise_mode": false,
    "half_basal_exercise_target": 160,
    "maxCOB": 120,
    "skip_neutral_temps": false,
    "remainingCarbsCap": 90,
    "enableUAM": true,
    "A52_risk_enable": false,
    "SMBInterval": 5,
    "enableSMB_with_COB": true,
    "enableSMB_with_temptarget": true,
    "allowSMB_with_high_temptarget": false,
    "enableSMB_always": true,
    "enableSMB_after_carbs": true,
    "maxSMBBasalMinutes": 90,
    "maxUAMSMBBasalMinutes": 60,
    "bolus_increment": 0.1,
    "carbsReqThreshold": 1,
    "current_basal": 0.7,
    "temptargetSet": true,
    "autosens_max": 1.2,
    "out_units": "mmol/L",
    "lgsThreshold": 72,
    "variable_sens": 72.0,
    "autoISF_version": "3.0.1",
    "enable_autoISF": true,
    "autoISF_max": 2.0,
    "autoISF_min": 0.5,
    "bgAccel_ISF_weight": 0.06,
    "bgBrake_ISF_weight": 0.04,
    "pp_ISF_weight": 0.02,
    "lower_ISFrange_weight": 0.2,
    "higher_ISFrange_weight": 0.4,
    "dura_ISF_weight": 0.5,
    "smb_delivery_ratio": 0.5,
    "smb_delivery_ratio_min": 0.5,
    "smb_delivery_ratio_max": 0.6,
    "smb_delivery_ratio_bg_range": 0.0,
    "smb_max_range_extension": 1.0,
    "enableSMB_EvenOn_OddOff_always": false,
    "iob_threshold_percent": 100,
    "profile_percentage": 100,
    "_log_path": "C:\\Users\\IngPPO1\\Desktop\\AAPS-Emulator\\data\\logs\\AndroidAPS.2026-01-15.0.log.zip"
  },
  {
    "__type__": "AutosensResult",
    "ratio": 1.0,
    "carbsAbsorbed": 0.0,
    "sensResult": "autosens disabled",
    "pastSensitivity": "",
    "ratioLimit": "",
    "ratioFromTdd": 1.0,
    "ratioFromCarbs": 1.0,
    "_log_path": "C:\\Users\\IngPPO1\\Desktop\\AAPS-Emulator\\data\\logs\\AndroidAPS.2026-01-15.0.log.zip"
  },
  {
    "__type__": "MealData",
    "carbs": 60.0,
    "mealCOB": 49.19877113813691,
    "slopeFromMaxDeviation": 0.0,
    "slopeFromMinDeviation": 1.1651111111111114,
    "lastBolusTime": 1768471607477,
    "lastCarbTime": 1768469117000,
    "usedMinCarbsImpact": 8.0,
    "_log_path": "C:\\Users\\IngPPO1\\Desktop\\AAPS-Emulator\\data\\logs\\AndroidAPS.2026-01-15.0.log.zip"
  },
  {
    "__type__": "RT",
    "algorithm": "AUTO_ISF",
    "runningDynamicIsf": true,
    "timestamp": 1768471829622,
    "temp": "absolute",
    "bg": 131.0,
    "tick": "+4",
    "eventualBG": 222.0,
    "targetBG": 90.0,
    "snoozeBG": null,
    "insulinReq": 1.25,
    "carbsReq": null,
    "carbsReqWithin": null,
    "units": null,
    "deliverAt": 1768471829622,
    "sensitivityRatio": 1.2,
    "reason": "COB: 49",
    "2": true,
    "Dev: 2": true,
    "4": true,
    "BGI: -0": true,
    "ISF: 4": true,
    "0": true,
    "CR: 15": true,
    "8": true,
    "Target: 5": true,
    "minPredBG 10": true,
    "minGuardBG 6": true,
    "IOBpredBG 2": true,
    "3": true,
    "COBpredBG 12": true,
    "UAMpredBG 3": true,
    "7; Eventual BG 12": true,
    "3 >": 5,
    "insulinReq 1.25; setting 60m low temp of 0.0U/h. Waiting 1m 18s to microbolus again.": true,
    "duration": 60,
    "rate": 0.0,
    "predBGs": {
      "__type__": "Predictions",
      "IOB": [
        131,
        135,
        137,
        139,
        139,
        139,
        138,
        137,
        134,
        131,
        128,
        124,
        119,
        114,
        110,
        106,
        101,
        97,
        93,
        90,
        86,
        83,
        79,
        76,
        73,
        71,
        68,
        66,
        63,
        61,
        59,
        57,
        55,
        54,
        52,
        51,
        50,
        48,
        47,
        46,
        46,
        45,
        44,
        43,
        43,
        42,
        42,
        41
      ],
      "ZT": [
        131,
        128,
        125,
        121,
        116,
        112,
        108,
        104,
        99,
        95,
        91,
        87,
        84,
        80,
        77,
        75,
        72,
        70,
        68,
        66,
        65,
        64,
        63,
        63,
        62,
        62,
        63,
        63,
        64,
        65,
        66,
        68,
        70,
        71,
        74,
        76,
        78,
        81,
        84,
        86,
        89
      ],
      "COB": [
        131,
        135,
        139,
        142,
        145,
        148,
        151,
        153,
        155,
        157,
        160,
        162,
        164,
        167,
        169,
        172,
        174,
        177,
        180,
        183,
        186,
        190,
        193,
        196,
        199,
        202,
        205,
        208,
        210,
        212,
        214,
        216,
        218,
        219,
        221,
        222,
        223,
        224,
        224,
        225,
        225,
        225,
        224,
        224,
        223,
        223,
        222
      ],
      "aCOB": null,
      "UAM": [
        131,
        135,
        138,
        140,
        142,
        143,
        143,
        143,
        142,
        141,
        140,
        138,
        136,
        134,
        131,
        128,
        125,
        122,
        118,
        114,
        111,
        107,
        104,
        101,
        98,
        95,
        93,
        90,
        88,
        86,
        84,
        82,
        80,
        78,
        77,
        75,
        74,
        73,
        72,
        71,
        70,
        69,
        69,
        68,
        67,
        67,
        66
      ]
    },
    "COB": 49.19877113813691,
    "IOB": 1.801,
    "variable_sens": 72.0,
    "isfMgdlForCarbs": null,
    "consoleLog": [],
    "consoleError": [
      "Sensitivity ratio set to 1.2 based on temp target of 90.0;",
      "Adjusting basal from 0.7 to 0.84;",
      "ISF from 86.4 to 72.0",
      "CR: 15.8",
      "----------------------------------",
      "start AutoISF 3.0.1",
      "----------------------------------",
      "User setting iobTH=100% disables iobTH method",
      "Loop allows AAPS power level",
      "SMB delivery ratio set to fixed value 0.5",
      "Parabola fit results were acceleration:-0.67",
      "correlation:0.9986",
      "duration:15.0m",
      "Parabolic fit extrapolates a maximum of 8",
      "1 in about 33.3 minutes",
      "acce_ISF adaptation is 0.97",
      "bg_ISF adaptation is 1.11",
      "pp_ISF adaptation is 1.09",
      "dura_ISF by-passed; bg is only 5.0 m at level 128.8",
      "strongest autoISF factor 1.11 weakened to 1.08 as bg decelerates already",
      "final ISF factor is 1.2 from low TT modifier",
      "----------------------------------",
      "end AutoISF",
      "----------------------------------",
      "SMB enabled due to enableSMB_always",
      "profile.sens: 86.39999999999999",
      "sens: 72.0",
      "CSF: 4.556962025316455",
      "Last carbs 45minutes ago; remainingCATime:3.6hours;18% carbs absorbed",
      "Carb Impact: 7.3 mg/dL per 5m; CI Duration: 3.6 hours; remaining CI (~2h peak): 3.1 mg/dL per 5m",
      {
        "__type__": "predCIs",
        "mg/dL/5m": true
      },
      ":7 7 7 7 6 6 6 6 6 6 5 5 5 5 5 5 4 4 4 4 4 4 3 3 3 3 3 3 2 2 2 2 2 2 1 1 1 1 1 1 0 0 0 0 0 0 0 0",
      "remainingCIs:      0 0 0 1 1 1 1 1 1 1 2 2 2 2 2 2 2 3 3 3 3 3 3 3 3 2 2 2 2 2 2 2 1 1 1 1 1 1 1 0 0 0 0 0 0 0 0 0",
      "UAM Impact: 7.3 mg/dL per 5m; UAM Duration: 1.6 hours",
      "EventualBG is 222.0 ;",
      "minPredBG: 180.0 minIOBPredBG: 41.0 minZTGuardBG: 62.0",
      "minCOBPredBG: 180.0",
      "minUAMPredBG: 66.0",
      "avgPredBG: 193.0 COB: 49.19877113813691 / 60.0",
      "BG projected to remain above 5",
      "0 for 240 minutes",
      "naive_eventualBG: 1.0 bgUndershoot: 64.0 zeroTempDuration 240 zeroTempEffect: 202 carbsReq: -64",
      "profile.maxSMBBasalMinutes: 90 profile.current_basal: 0.7",
      "naive_eventualBG 1.0",
      "60m 0.0U/h temp needed; last bolus 3.7m ago; maxBolus: 1.0"
    ],
    "_log_path": "C:\\Users\\IngPPO1\\Desktop\\AAPS-Emulator\\data\\logs\\AndroidAPS.2026-01-15.0.log.zip"
  }
]